[
    {
        "receipt_number": 1,
        "receipt_type": "receipt.retailMeal",
        "merchant_name": "\u0411\u0418\u041b\u041b\u0410 \u0411\u042a\u041b\u0413\u0410\u0420\u0418\u042f \u0415\u041e\u041e\u0414",
        "transaction_date": "2013-03-26",
        "items": [
            {
                "description": "\u0411\u0410\u041d\u0410\u041d\u0418",
                "quantity": 0.252,
                "price": 2.59,
                "total_price": 0.65
            }
        ],
        "subtotal": null,
        "tax": null,
        "tip": null,
        "total": 0.65
    }
]