[
    {
        "receipt_number": 1,
        "receipt_type": "receipt.retailMeal",
        "merchant_name": "MR. D.I.Y. (M) SDN BHD",
        "transaction_date": "2018-03-23",
        "items": [
            {
                "description": "DOUBLE EXT BOX 10Y 40/016 CBD4110\nWA21 - 20",
                "quantity": 1.0,
                "price": 25.9,
                "total_price": 25.9
            },
            {
                "description": "PLASTIC BAGS",
                "quantity": 1.0,
                "price": 0.2,
                "total_price": 0.2
            }
        ],
        "subtotal": null,
        "tax": 1.48,
        "tip": null,
        "total": 26.1
    }
]