[
    {
        "receipt_number": 1,
        "receipt_type": "receipt.gas",
        "merchant_name": "FUEL KING SERVICE CENTER",
        "transaction_date": "2017-06-03",
        "items": [
            {
                "description": "EURO GAS91",
                "quantity": null,
                "price": 43.95,
                "total_price": 1006.46
            },
            {
                "description": "Acc Dis/Chg-Cr",
                "quantity": null,
                "price": null,
                "total_price": -68.7
            }
        ],
        "subtotal": null,
        "tax": 100.47,
        "tip": null,
        "total": 937.76
    }
]