[
    {
        "receipt_number": 1,
        "receipt_type": "receipt.retailMeal",
        "merchant_name": null,
        "transaction_date": "2018-12-15",
        "items": [
            {
                "description": "SALM HONEY",
                "quantity": 1.0,
                "price": null,
                "total_price": 28.95
            },
            {
                "description": "SHORTRIB s",
                "quantity": 1.0,
                "price": null,
                "total_price": 27.95
            },
            {
                "description": "CHEESECAKE ST",
                "quantity": 1.0,
                "price": null,
                "total_price": 8.5
            },
            {
                "description": "DIET COKE",
                "quantity": 1.0,
                "price": null,
                "total_price": 3.95
            }
        ],
        "subtotal": 69.35,
        "tax": 7.35,
        "tip": null,
        "total": 80.0
    }
]