[
    {
        "receipt_number": 1,
        "receipt_type": "receipt.retailMeal",
        "merchant_name": "Lilly O'Briens",
        "transaction_date": "2016-03-15",
        "items": [
            {
                "description": "Jameson",
                "quantity": null,
                "price": null,
                "total_price": 8.0
            },
            {
                "description": "Tomato Juice",
                "quantity": 1.0,
                "price": null,
                "total_price": 3.0
            },
            {
                "description": "Guinness",
                "quantity": null,
                "price": null,
                "total_price": 6.0
            },
            {
                "description": "Stella",
                "quantity": null,
                "price": null,
                "total_price": 5.0
            }
        ],
        "subtotal": 23.0,
        "tax": 1.87,
        "tip": null,
        "total": 23.0
    }
]