[
    {
        "receipt_number": 1,
        "receipt_type": "receipt.retailMeal",
        "merchant_name": "Restaurant McDonald's Sipean",
        "transaction_date": "2017-08-07",
        "items": [
            {
                "description": "Chicken Caesar",
                "quantity": 1.0,
                "price": 6.9,
                "total_price": 6.9
            },
            {
                "description": "Manhattan",
                "quantity": null,
                "price": 6.9,
                "total_price": 6.9
            },
            {
                "description": "Moyen Frite",
                "quantity": 1.0,
                "price": 2.5,
                "total_price": 2.5
            }
        ],
        "subtotal": null,
        "tax": 1.48,
        "tip": null,
        "total": 6.3
    }
]